lucterios/__init__.py
lucterios/CORE/__init__.py
lucterios/CORE/build
lucterios/CORE/editors.py
lucterios/CORE/import_drivers.py
lucterios/CORE/models.py
lucterios/CORE/parameters.py
lucterios/CORE/tests.py
lucterios/CORE/tests_framework.py
lucterios/CORE/tests_plugins.py
lucterios/CORE/tests_usergroup.py
lucterios/CORE/views.py
lucterios/CORE/views_auth.py
lucterios/CORE/views_usergroup.py
lucterios/CORE/xferprint.py
lucterios/CORE/docs/build_en/doctrees/architecture.doctree
lucterios/CORE/docs/build_en/doctrees/environment.pickle
lucterios/CORE/docs/build_en/doctrees/groups.doctree
lucterios/CORE/docs/build_en/doctrees/index.doctree
lucterios/CORE/docs/build_en/doctrees/password.doctree
lucterios/CORE/docs/build_en/doctrees/users.doctree
lucterios/CORE/docs/build_fr/doctrees/architecture.doctree
lucterios/CORE/docs/build_fr/doctrees/environment.pickle
lucterios/CORE/docs/build_fr/doctrees/groups.doctree
lucterios/CORE/docs/build_fr/doctrees/index.doctree
lucterios/CORE/docs/build_fr/doctrees/password.doctree
lucterios/CORE/docs/build_fr/doctrees/users.doctree
lucterios/CORE/docs/en/Makefile
lucterios/CORE/docs/en/architecture.rst
lucterios/CORE/docs/en/conf.py
lucterios/CORE/docs/en/groups.rst
lucterios/CORE/docs/en/index.rst
lucterios/CORE/docs/en/password.rst
lucterios/CORE/docs/en/users.rst
lucterios/CORE/docs/en/_static/group.png
lucterios/CORE/docs/en/_static/group_modify.png
lucterios/CORE/docs/en/_static/password.png
lucterios/CORE/docs/en/_static/user_info.png
lucterios/CORE/docs/en/_static/user_permissions.png
lucterios/CORE/docs/en/_static/users.png
lucterios/CORE/docs/fr/Makefile
lucterios/CORE/docs/fr/architecture.rst
lucterios/CORE/docs/fr/conf.py
lucterios/CORE/docs/fr/groups.rst
lucterios/CORE/docs/fr/index.rst
lucterios/CORE/docs/fr/password.rst
lucterios/CORE/docs/fr/users.rst
lucterios/CORE/docs/fr/_static/group.png
lucterios/CORE/docs/fr/_static/group_modify.png
lucterios/CORE/docs/fr/_static/password.png
lucterios-2.7.1.24071814.dist-info/LICENSE
lucterios-2.7.1.24071814.dist-info/METADATA
lucterios-2.7.1.24071814.dist-info/WHEEL
lucterios-2.7.1.24071814.dist-info/top_level.txt
lucterios-2.7.1.24071814.dist-info/RECORD
