Metadata-Version: 2.1
Name: lucterios
Version: 2.7.1.24071814
Summary: Lucterios framework.
Home-page: http://www.lucterios.org
Author: Lucterios
Author-email: info@lucterios.org
License: GNU General Public License v3
Platform: Any
Classifier: Development Status :: 5 - Production/Stable
Classifier: Environment :: Web Environment
Classifier: Framework :: Django :: 4.2
Classifier: Intended Audience :: Developers
Classifier: Intended Audience :: End Users/Desktop
Classifier: License :: OSI Approved :: GNU General Public License v3 (GPLv3)
Classifier: Natural Language :: English
Classifier: Natural Language :: French
Classifier: Operating System :: OS Independent
Classifier: Programming Language :: Python :: 3.8
Classifier: Programming Language :: Python :: 3.9
Classifier: Programming Language :: Python :: 3.10
Classifier: Programming Language :: Python :: 3.11
Classifier: Topic :: Database :: Front-Ends
License-File: LICENSE
Requires-Dist: pip
Requires-Dist: importlib-metadata
Requires-Dist: Django ~=4.2
Requires-Dist: django-fsm ~=2.8
Requires-Dist: lxml ~=5.1
Requires-Dist: lxml-html-clean
Requires-Dist: Pillow ~=10.2
Requires-Dist: reportlab ~=4.1
Requires-Dist: APScheduler ~=3.10
Requires-Dist: Babel ~=2.14
Requires-Dist: pyqt5 ~=5.15
Requires-Dist: odfpy ~=1.4
Requires-Dist: openpyxl ~=3.1
Requires-Dist: xlrd ~=2.0
Requires-Dist: pandas ~=2.0
Requires-Dist: waitress
